slcl1butils/__init__.py
slcl1butils/config.yaml
slcl1butils/conversion_polar_cartesian.py
slcl1butils/cwave_parameters_computation_example.ipynb
slcl1butils/get_config.py
slcl1butils/get_polygons_from_l1b.py
slcl1butils/raster_readers.py
slcl1butils/spectrum_clockwise_to_trigo.py
slcl1butils/spectrum_rotation.py
slcl1butils/symmetrize_l1b_spectra.py
slcl1butils/utils.py
slcl1butils/coloc/__init__.py
slcl1butils/coloc/coloc.py
slcl1butils/compute/__init__.py
slcl1butils/compute/compute_from_l1b.py
slcl1butils/compute/cwave.py
slcl1butils/compute/macs.py
slcl1butils/compute/stack_iw_l1b.py
slcl1butils/compute/stack_wv_l1c_monthly.py
slcl1butils/plotting/__init__.py
slcl1butils/plotting/add_azimuth_cutoff_lines_on_polar_spec_fig.py
slcl1butils/plotting/display_one_spectra.py
slcl1butils/plotting/display_xspectra_grid.py
slcl1butils/plotting/plotting_L1B_geometry_with_holoview_example.ipynb
slcl1butils/plotting/plotting_L1B_variables_with_holoview_example.ipynb
slcl1butils/plotting/quadmeshgeoviewsL1B.py
slcl1butils/plotting/spectra_plot_circles_wavenumbers.py
slcl1butils/plotting/wallpaper.py
slcl1butils/scripts/do_IW_L1C_SAFE_from_L1B_SAFE.pbs
slcl1butils/scripts/do_IW_L1C_SAFE_from_L1B_SAFE.py
slcl1butils/scripts/do_IW_L1C_SAFE_from_L1B_SAFE_prun.py
slcl1butils/scripts/do_WV_L1C_SAFE_from_L1B_SAFE.pbs
slcl1butils/scripts/do_WV_L1C_SAFE_from_L1B_SAFE.py
slcl1butils/scripts/do_WV_L1C_SAFE_from_L1B_SAFE_prun.py
slcl1butils-2023.9.7.dist-info/LICENSE
slcl1butils-2023.9.7.dist-info/METADATA
slcl1butils-2023.9.7.dist-info/WHEEL
slcl1butils-2023.9.7.dist-info/entry_points.txt
slcl1butils-2023.9.7.dist-info/top_level.txt
slcl1butils-2023.9.7.dist-info/RECORD
