Metadata-Version: 2.1
Name: slcl1butils
Version: 2023.9.7
Summary: Python library to exploit SAR IFREMER L1B products
Author: Alexis Mouche
License: GPL-3.0
Keywords: SAR,wave,reseach,cross-spectra
Classifier: Programming Language :: Python :: 3
Requires-Python: >=3.9
License-File: LICENSE
Requires-Dist: PyYAML
Requires-Dist: xarray
Requires-Dist: numpy
Requires-Dist: netCDF4
Requires-Dist: shapely
Requires-Dist: xarray-datatree
Requires-Dist: tqdm
Requires-Dist: zarr
Requires-Dist: fsspec
Requires-Dist: matplotlib
Requires-Dist: scipy
Requires-Dist: aiohttp
